llmeval/__init__.py
llmeval/client.py
llmeval/exceptions.py
llmeval/models.py
llmeval/utils.py
llmeval_sdk-0.1.8.dist-info/METADATA
llmeval_sdk-0.1.8.dist-info/WHEEL
llmeval_sdk-0.1.8.dist-info/top_level.txt
llmeval_sdk-0.1.8.dist-info/RECORD
